Workbook

Sheet README
A1: State Marching Contest Medal Demand Forecasting & Inventory Optimization
A3: Project Overview
A4: This project uses historical medal demand, forecasting models, and inventory analysis to develop data-driven purchasing recommendations for an annual state marching contest. The objective is to balance sufficient medal availability with responsible purcahsing and inventory management
A6: Business Problem
A7: A fictional statewide marching contest must make advance purchasing decisions for three medal divisions. Ordering too few medals creates a risk of shortages, potentially leaving participants without awards, while ordering too many increases purchasing costs and creates excess inventory. Because unused medals can be carried forward into future years, purchasing decisions must account for historical demand, available inventory, and uncertainty in future demand. This project addresses that challenge by comparing forecasting methods and translating projected demand into actionable purchasing recommendations under baseline and conservative inventory scenarios.
A9: Data Sources and Historical Coverage
A10: This project uses an entirely synthetic dataset representing fictional marching contest medal demand from 2016–2025, organized by year, classification, and medal division (1st, 2nd, and 3rd). All historical demand, purchasing quantities, inventory balances, and cost assumptions are fictional and were created for portfolio demonstration purposes. Historical medal demand is aggregated across classifications to produce division-level forecasts. The dataset incorporates a simulated expansion from five classifications to seven in 2018, demonstrating how changes in data structure can be accommodated in historical analysis. Forecasting models are evaluated using historical observations from 2019–2025. The workbook also includes fictional 2026 purchasing plans and preliminary 2027 inventory recommendations. The model is designed to incorporate future actual demand and inventory results, allowing purchasing recommendations to be recalculated as new information becomes available.
A12: Forecasting Methodology
A13: Three forecasting approaches were evaluated: 3-Year Simple Moving Average, Weighted Moving Average, and Simple Exponential Smoothing. Each method was assessed using historical forecast performance from 2019–2025, including Mean Absolute Error (MAE), Mean Absolute Percentage Error (MAPE), and Forecast Bias. Rather than applying a single forecasting method across all medal divisions, the analysis evaluates model performance independently for each division. Model selection prioritizes lower MAE and MAPE while considering forecast bias and the operational risks associated with underestimating demand. The selected models generate preliminary demand forecasts for 2026 and 2027. These forecasts are incorporated into inventory planning calculations that account for beginning inventory, projected medal demand, safety stock, and alternative purchasing scenarios. The resulting recommendations help quantify the trade-off between inventory availability and purchasing costs.
A15: Division | B15: Selected Model | C15: Parameters
A16: 1st Division | B16: Exponential Smoothing | C16: α = 0.5
A17: 2nd Division | B17: Exponential Smoothing | C17: α = 0.5
A18: 3rd Division | B18: Weighted Moving Average | C18: 0.5 / 0.3 / 0.2
A20: Inventory Optimization Methodology
A21: Forecasted medal demand is combined with projected beginning inventory and safety stock to calculate recommended purchasing quantities. Because unused medals can be carried forward into subsequent years, the model accounts for available inventory before recommending additional purchases. Projected ending inventory from 2026 becomes the estimated beginning inventory for 2027, allowing purchasing decisions to reflect inventory already on hand. Safety stock is informed by historical forecasting errors to provide a buffer against demand exceeding expectations. The model evaluates two purchasing scenarios: - Baseline Scenario: Uses twice the historical Mean Absolute Error (MAE) as the safety stock target. - Conservative Scenario: Uses the greater of the baseline safety stock target or the largest historical underforecast. These scenarios allow decision-makers to evaluate the additional purchasing cost associated with greater inventory protection. The safety stock assumptions are illustrative planning rules and do not guarantee that shortages will be eliminated.
A23: Purchasing Calculations
A24: Recommended purchase quantities are calculated by rounding forecast demand up to the nearest whole medal, adding the applicable safety stock target, and subtracting projected beginning inventory. Purchase recommendations cannot be negative, ensuring that sufficient existing inventory results in a recommendation of zero additional medals. Recommended Purchases = MAX(0, Rounded Forecast Demand + Safety Stock − Projected Beginning Inventory) The baseline scenario uses safety stock equal to twice the historical Mean Absolute Error (MAE), while the conservative scenario uses the greater of baseline safety stock or the largest historical underforecast. All recommended purchase quantities are expressed as whole medals.
A26: Calculation | B26: Formula
A27: Rounded Demand | B27: ROUNDUP(Forecast Demand, 0)
A28: Baseline Safety Stock | B28: ROUNDUP(2 x Historical MAE, 0)
A29: Conservative Safety Stock | B29: MAX(Baseline Safety Stock, Maximum Historical Underforecast)
A30: Recommended Purchase | B30: MAX(0, Rounded Demand + Safety Stock - Beginning Inventory)
A32: Post-Contest Update Process
A33: After the fictional 2026 marching contest, enter the actual medals awarded for each classification and medal division in the `Historical Data` worksheet. All 21 classification-level values must be entered, including zeros where applicable, before complete actual demand totals are available. Next, enter the physically verified ending inventory for each medal division in the `Inventory Analysis` worksheet. The workbook compares actual ending inventory against the expected balance calculated from beginning inventory, purchases, and medals awarded. Any discrepancies are identified as inventory adjustments for investigation. Once actual demand and inventory results are entered, the selected forecasting models update the 2027 demand forecasts, and the purchasing recommendations automatically recalculate using the verified inventory balances. For portfolio demonstration purposes, any future results entered into this workbook should also be fictional or otherwise authorized for public use.
A35: Key Findings & Business Impact
A36: Based on the synthetic 2027 demand forecasts and projected beginning inventory, the baseline purchasing scenario recommends 2,039 medals at an estimated cost of $6,117. The conservative scenario recommends 2,213 medals at an estimated cost of $6,639. For an additional $522 (approximately 8.5%), the conservative scenario provides 174 additional medals to help mitigate the risk of demand exceeding forecasts. These recommendations demonstrate how forecasting accuracy, inventory availability, and purchasing costs can be evaluated together to support transparent, data-driven purchasing decisions. All demand, inventory, purchasing, and cost figures are fictional and used solely for portfolio demonstration purposes.
A38: Assumptions & Limitations
A39: This project uses entirely synthetic historical demand, purchasing, and inventory data to demonstrate forecasting and inventory planning techniques. The analysis assumes that historical demand patterns provide a reasonable basis for estimating future demand. Forecast accuracy may be affected by changes in contest participation, classification structures, or other factors not explicitly incorporated into the models. Safety stock is calculated using historical forecast errors rather than a statistically guaranteed service level. Consequently, neither purchasing scenario eliminates the possibility of shortages. The analysis assumes unused medals remain available for future contests and that recorded inventory quantities are accurate. Estimated purchasing costs use a fictional unit cost of $3.00 per medal, consisting of a $2.85 medal price and a $0.15 shipping allowance. These amounts are illustrative and do not represent actual vendor pricing. The preliminary 2027 purchasing recommendations rely on projected 2026 ending inventory. Once actual 2026 demand and physical inventory counts become available, the recommendations should be recalculated before purchasing decisions are finalized.
A41: Technical Skills & Project Conclusion
A42: Microsoft Excel: Structured tables, SUMIF, INDEX/MATCH, IF statements, conditional logic, dynamic worksheet references, and formula-driven calculations across multiple worksheets.
A43: Forecasting & Statistical Analysis: 3-Year Simple Moving Average, Weighted Moving Average, Simple Exponential Smoothing, historical forecast evaluation, Mean Absolute Error (MAE), Mean Absolute Percentage Error (MAPE), and forecast bias analysis.
A44: Inventory & Financial Analysis: Inventory reconciliation, projected inventory balances, safety stock calculations, demand-based purchasing recommendations, scenario analysis, and purchasing cost estimation.
A45: Data Visualization & Decision Support: Executive dashboard development, KPI reporting, historical forecasting risk analysis, and automated purchasing recommendations that support data-driven decision-making.
A47: Project Conclusion
A48: This project demonstrates how synthetic historical data can be transformed into a repeatable forecasting and inventory planning solution. By evaluating multiple forecasting methods, accounting for existing inventory, and comparing alternative purchasing scenarios, the workbook translates analytical results into actionable recommendations. The model is designed to incorporate new demand observations and verified inventory balances, allowing forecasts and purchasing recommendations to evolve as additional information becomes available. Ultimately, this project demonstrates how forecasting, inventory management, and financial analysis can work together to support informed, data-driven operational decisions.

Sheet Historical Data
A1: Classification | B1: Medal Type | C1: 2016 | D1: 2017 | E1: 2018 | F1: 2019 | G1: 2020 | H1: 2021 | I1: 2022 | J1: 2023 | K1: 2024 | L1: 2025 | M1: 2026
A2: 1A | B2: 1st Division | C2: 25 | D2: 30 | E2: 34 | F2: 47 | G2: 53 | H2: 34 | I2: 23 | J2: 42 | K2: 49 | L2: 31
A3: 1A | B3: 2nd Division | C3: 26 | D3: 34 | E3: 16 | F3: 32 | G3: 54 | H3: 24 | I3: 50 | J3: 23 | K3: 52 | L3: 43
A4: 1A | B4: 3rd Division | C4: 25 | D4: 19 | E4: 22 | F4: 30 | G4: 27 | H4: 22 | I4: 27 | J4: 43 | K4: 37 | L4: 39
A5: 2A | B5: 1st Division | C5: 31 | D5: 80 | E5: 56 | F5: 84 | G5: 75 | H5: 64 | I5: 85 | J5: 80 | K5: 48 | L5: 38
A6: 2A | B6: 2nd Division | C6: 72 | D6: 45 | E6: 36 | F6: 48 | G6: 80 | H6: 30 | I6: 78 | J6: 44 | K6: 68 | L6: 34
A7: 2A | B7: 3rd Division | C7: 54 | D7: 42 | E7: 64 | F7: 81 | G7: 37 | H7: 83 | I7: 59 | J7: 67 | K7: 58 | L7: 58
A8: 3A | B8: 1st Division | C8: 109 | D8: 97 | E8: 103 | F8: 91 | G8: 91 | H8: 110 | I8: 85 | J8: 61 | K8: 95 | L8: 63
A9: 3A | B9: 2nd Division | C9: 98 | D9: 82 | E9: 62 | F9: 74 | G9: 58 | H9: 69 | I9: 62 | J9: 54 | K9: 108 | L9: 94
A10: 3A | B10: 3rd Division | C10: 72 | D10: 76 | E10: 94 | F10: 80 | G10: 100 | H10: 81 | I10: 110 | J10: 71 | K10: 75 | L10: 48
A11: 4A | B11: 1st Division | C11: 95 | D11: 115 | E11: 93 | F11: 122 | G11: 73 | H11: 113 | I11: 111 | J11: 109 | K11: 72 | L11: 113
A12: 4A | B12: 2nd Division | C12: 123 | D12: 64 | E12: 109 | F12: 82 | G12: 117 | H12: 131 | I12: 82 | J12: 78 | K12: 72 | L12: 138
A13: 4A | B13: 3rd Division | C13: 62 | D13: 119 | E13: 98 | F13: 103 | G13: 78 | H13: 131 | I13: 124 | J13: 133 | K13: 133 | L13: 85
... A16: 5A | B16: 3rd Division | C16: 151 | D16: 121 | E16: 149 | F16: 131 | G16: 150 | H16: 86 | I16: 122 | J16: 119 | K16: 165 | L16: 103
A17: 6A | B17: 1st Division | E17: 138 | F17: 133 | G17: 175 | H17: 93 | I17: 145 | J17: 107 | K17: 155 | L17: 164
A18: 6A | B18: 2nd Division | E18: 189 | F18: 91 | G18: 190 | H18: 94 | I18: 133 | J18: 148 | K18: 175 | L18: 136
A19: 6A | B19: 3rd Division | E19: 152 | F19: 190 | G19: 173 | H19: 186 | I19: 152 | J19: 91 | K19: 137 | L19: 113
A20: 7A | B20: 1st Division | E20: 113 | F20: 155 | G20: 204 | H20: 209 | I20: 182 | J20: 138 | K20: 143 | L20: 170
A21: 7A | B21: 2nd Division | E21: 197 | F21: 161 | G21: 182 | H21: 165 | I21: 127 | J21: 205 | K21: 132 | L21: 174
A22: 7A | B22: 3rd Division | E22: 107 | F22: 190 | G22: 166 | H22: 141 | I22: 143 | J22: 164 | K22: 148 | L22: 111
A24: Ordered: | B24: First | C24: 650 | D24: 465 | E24: 850 | I24: 600 | J24: 853 | K24: 500 | L24: 722 | M24: 800
B25: Second | C25: 650 | D25: 430 | E25: 750 | I25: 410 | J25: 500 | K25: 470 | L25: 668 | M25: 550
B26: Third | C26: 650 | D26: 375 | E26: 100 | I26: 380 | J26: 640 | K26: 620 | L26: 617 | M26: 425
A27: Left Over: | B27: First | I27: 97 | J27: 333 | K27: 129 | L27: 132
B28: Second | I28: 285 | J28: 360 | K28: 185 | L28: 287
B29: Third | I29: 88 | J29: 215 | K29: 189 | L29: 400

Sheet 1st Division
A1: Year | B1: Actual Demand | C1: Average Forecast | D1: Error | E1: Absolute Error | F1: Absolute % Error | G1: Weighted Forecast | H1: Error | I1: Absolute Error | J1: Absolute % Error | K1: Alpha | L1: Exponential Smoothing | M1: Error | N1: Absolute Error | O1: Absolute % Error
A2: 2016 | B2: =SUMIFS(INDEX('Historical Data'!$C$2:$ZZ$100,0,MATCH(A2&"",'Historical Data'!$C$1:$ZZ$1,0)),'Historical Data'!$B$2:$B$100,"1st Division") -> 418 | K2: 0.5 | Q2: 2026 FORECAST | U2: BEST MODEL | Y2: HISTORICAL MAE | AC2: The 2027 forecast carries forward the 2026 exponential smoothing forecast because actual 2026 demand is not yet available. Once 2026 actual demand is recorded, the 2027 forecast should be recalculated using the updated smoothing equation.
A3: 2017 | B3: =SUMIFS(INDEX('Historical Data'!$C$2:$ZZ$100,0,MATCH(A3&"",'Historical Data'!$C$1:$ZZ$1,0)),'Historical Data'!$B$2:$B$100,"1st Division") -> 404 | L3: =B2 -> 418
A4: 2018 | B4: =SUMIFS(INDEX('Historical Data'!$C$2:$ZZ$100,0,MATCH(A4&"",'Historical Data'!$C$1:$ZZ$1,0)),'Historical Data'!$B$2:$B$100,"1st Division") -> 626 | L4: =$K$2*B3+(1-$K$2)*L3 -> 411 | Q4: ='Model Comparison'!J2 -> 708.69922 | U4: =_xlfn.XLOOKUP("Best",'Model Comparison'!G2:G4, 'Model Comparison'!B2:B4) -> Exponential Smoothing | Y4: =MIN('Model Comparison'!C2:C4) -> 92.739955
A5: 2019 | B5: =SUMIFS(INDEX('Historical Data'!$C$2:$ZZ$100,0,MATCH(A5&"",'Historical Data'!$C$1:$ZZ$1,0)),'Historical Data'!$B$2:$B$100,"1st Division") -> 719 | C5: =AVERAGE(B2:B4) -> 482.66667 | D5: =B5-C5 -> 236.33333 | E5: =ABS(D5) -> 236.33333 | F5: =IFERROR(E5/B5,"") -> 0.32869726 | G5: =(B4*0.5)+(B3*0.3)+(B2*0.2) -> 517.8 | H5: =B5-G5 -> 201.2 | I5: =ABS(H5) -> 201.2 | J5: =IFERROR(I5/B5,"") -> 0.2798331 | L5: =$K$2*B4+(1-$K$2)*L4 -> 518.5 | M5: =B5-L5 -> 200.5 | N5: =ABS(M5) -> 200.5 | O5: =IFERROR(N5/B5,"") -> 0.27885953 | P5: =MAX(0,B5-L5) -> 200.5
A6: 2020 | B6: =SUMIFS(INDEX('Historical Data'!$C$2:$ZZ$100,0,MATCH(A6&"",'Historical Data'!$C$1:$ZZ$1,0)),'Historical Data'!$B$2:$B$100,"1st Division") -> 806 | C6: =AVERAGE(B3:B5) -> 583 | D6: =B6-C6 -> 223 | E6: =ABS(D6) -> 223 | F6: =IFERROR(E6/B6,"") -> 0.27667494 | G6: =(B5*0.5)+(B4*0.3)+(B3*0.2) -> 628.1 | H6: =B6-G6 -> 177.9 | I6: =ABS(H6) -> 177.9 | J6: =IFERROR(I6/B6,"") -> 0.2207196 | L6: =$K$2*B5+(1-$K$2)*L5 -> 618.75 | M6: =B6-L6 -> 187.25 | N6: =ABS(M6) -> 187.25 | O6: =IFERROR(N6/B6,"") -> 0.2323201 | P6: =MAX(0,B6-L6) -> 187.25
A7: 2021 | B7: =SUMIFS(INDEX('Historical Data'!$C$2:$ZZ$100,0,MATCH(A7&"",'Historical Data'!$C$1:$ZZ$1,0)),'Historical Data'!$B$2:$B$100,"1st Division") -> 714 | C7: =AVERAGE(B4:B6) -> 717 | D7: =B7-C7 -> -3 | E7: =ABS(D7) -> 3 | F7: =IFERROR(E7/B7,"") -> 0.0042016807 | G7: =(B6*0.5)+(B5*0.3)+(B4*0.2) -> 743.9 | H7: =B7-G7 -> -29.9 | I7: =ABS(H7) -> 29.9 | J7: =IFERROR(I7/B7,"") -> 0.041876751 | L7: =$K$2*B6+(1-$K$2)*L6 -> 712.375 | M7: =B7-L7 -> 1.625 | N7: =ABS(M7) -> 1.625 | O7: =IFERROR(N7/B7,"") -> 0.0022759104 | P7: =MAX(0,B7-L7) -> 1.625
A8: 2022 | B8: =SUMIFS(INDEX('Historical Data'!$C$2:$ZZ$100,0,MATCH(A8&"",'Historical Data'!$C$1:$ZZ$1,0)),'Historical Data'!$B$2:$B$100,"1st Division") -> 770 | C8: =AVERAGE(B5:B7) -> 746.33333 | D8: =B8-C8 -> 23.666667 | E8: =ABS(D8) -> 23.666667 | F8: =IFERROR(E8/B8,"") -> 0.030735931 | G8: =(B7*0.5)+(B6*0.3)+(B5*0.2) -> 742.6 | H8: =B8-G8 -> 27.4 | I8: =ABS(H8) -> 27.4 | J8: =IFERROR(I8/B8,"") -> 0.035584416 | L8: =$K$2*B7+(1-$K$2)*L7 -> 713.1875 | M8: =B8-L8 -> 56.8125 | N8: =ABS(M8) -> 56.8125 | O8: =IFERROR(N8/B8,"") -> 0.073782468 | P8: =MAX(0,B8-L8) -> 56.8125
A9: 2023 | B9: =SUMIFS(INDEX('Historical Data'!$C$2:$ZZ$100,0,MATCH(A9&"",'Historical Data'!$C$1:$ZZ$1,0)),'Historical Data'!$B$2:$B$100,"1st Division") -> 624 | C9: =AVERAGE(B6:B8) -> 763.33333 | D9: =B9-C9 -> -139.33333 | E9: =ABS(D9) -> 139.33333 | F9: =IFERROR(E9/B9,"") -> 0.2232906 | G9: =(B8*0.5)+(B7*0.3)+(B6*0.2) -> 760.4 | H9: =B9-G9 -> -136.4 | I9: =ABS(H9) -> 136.4 | J9: =IFERROR(I9/B9,"") -> 0.21858974 | L9: =$K$2*B8+(1-$K$2)*L8 -> 741.59375 | M9: =B9-L9 -> -117.59375 | N9: =ABS(M9) -> 117.59375 | O9: =IFERROR(N9/B9,"") -> 0.18845152 | P9: =MAX(0,B9-L9) -> 0
A10: 2024 | B10: =SUMIFS(INDEX('Historical Data'!$C$2:$ZZ$100,0,MATCH(A10&"",'Historical Data'!$C$1:$ZZ$1,0)),'Historical Data'!$B$2:$B$100,"1st Division") -> 666 | C10: =AVERAGE(B7:B9) -> 702.66667 | D10: =B10-C10 -> -36.666667 | E10: =ABS(D10) -> 36.666667 | F10: =IFERROR(E10/B10,"") -> 0.055055055 | G10: =(B9*0.5)+(B8*0.3)+(B7*0.2) -> 685.8 | H10: =B10-G10 -> -19.8 | I10: =ABS(H10) -> 19.8 | J10: =IFERROR(I10/B10,"") -> 0.02972973 | L10: =$K$2*B9+(1-$K$2)*L9 -> 682.79688 | M10: =B10-L10 -> -16.796875 | N10: =ABS(M10) -> 16.796875 | O10: =IFERROR(N10/B10,"") -> 0.025220533 | P10: =MAX(0,B10-L10) -> 0
A11: 2025 | B11: =SUMIFS(INDEX('Historical Data'!$C$2:$ZZ$100,0,MATCH(A11&"",'Historical Data'!$C$1:$ZZ$1,0)),'Historical Data'!$B$2:$B$100,"1st Division") -> 743 | C11: =AVERAGE(B8:B10) -> 686.66667 | D11: =B11-C11 -> 56.333333 | E11: =ABS(D11) -> 56.333333 | F11: =IFERROR(E11/B11,"") -> 0.075818753 | G11: =(B10*0.5)+(B9*0.3)+(B8*0.2) -> 674.2 | H11: =B11-G11 -> 68.8 | I11: =ABS(H11) -> 68.8 | J11: =IFERROR(I11/B11,"") -> 0.092597577 | L11: =$K$2*B10+(1-$K$2)*L10 -> 674.39844 | M11: =B11-L11 -> 68.601562 | N11: =ABS(M11) -> 68.601562 | O11: =IFERROR(N11/B11,"") -> 0.092330501 | P11: =MAX(0,B11-L11) -> 68.601562
D12: =AVERAGE(D5:D11) -> 51.47619 | E12: =AVERAGE(E5:E11) -> 102.61905 | F12: =AVERAGE(F5:F11) -> 0.14206775 | H12: =AVERAGE(H5:H11) -> 41.314286 | I12: =AVERAGE(I5:I11) -> 94.485714 | J12: =AVERAGE(J5:J11) -> 0.13127585 | M12: =AVERAGE(M5:M11) -> 54.342634 | N12: =AVERAGE(N5:N11) -> 92.739955 | O12: =AVERAGE(O5:O11) -> 0.12760579
A14: 2026 | B14: =IF(COUNT('Historical Data'!M2,'Historical Data'!M5,'Historical Data'!M8,'Historical Data'!M11,'Historical Data'!M14,'Historical Data'!M17,'Historical Data'!M20)=7,SUM('Historical Data'!M2,'Historical Data'!M5,'Historical Data'!M8,'Historical Data'!M11,'Historical Data'!M14,'Historical Data'!M17,'Historical Data'!M20),"") | C14: =AVERAGE(B9:B11) -> 677.66667 | G14: =(B11*0.5)+(B10*0.3)+(B9*0.2) -> 696.1 | L14: =$K$2*B11+(1-$K$2)*L11 -> 708.69922
A15: 2027 | L15: =IF(ISNUMBER(B14),$K$2*B14+(1-$K$2)*L14,L14) -> 708.69922
L19: Largest Underforecast | M19: =MAX(P5:P11) -> 200.5
L20: Average Underforecast | M20: =AVERAGE(P5:P11) -> 73.541295
L21: Historical Coverage | M21: =COUNTIF(P5:P11, "<=105")/COUNT(P5:P11) -> 0.71428571

Sheet 2nd Division
A1: Year | B1: Actual Demand | C1: Average Forecast | D1: Error | E1: Absolute Error | F1: Absolute % Error | G1: Weighted Forecast | H1: Error | I1: Absolute Error | J1: Absolute % Error | K1: Alpha | L1: Exponential Smoothing | M1: Error | N1: Absolute Error | O1: Absolute % Error
A2: 2016 | B2: =SUMIFS(INDEX('Historical Data'!$C$2:$ZZ$100,0,MATCH(A2&"",'Historical Data'!$C$1:$ZZ$1,0)),'Historical Data'!$B$2:$B$100,"2nd Division") -> 467 | K2: 0.5 | Q2: 2026 FORECAST | U2: BEST MODEL | Y2: HISTORICAL MAE
A3: 2017 | B3: =SUMIFS(INDEX('Historical Data'!$C$2:$ZZ$100,0,MATCH(A3&"",'Historical Data'!$C$1:$ZZ$1,0)),'Historical Data'!$B$2:$B$100,"2nd Division") -> 349 | L3: =B2 -> 467
A4: 2018 | B4: =SUMIFS(INDEX('Historical Data'!$C$2:$ZZ$100,0,MATCH(A4&"",'Historical Data'!$C$1:$ZZ$1,0)),'Historical Data'!$B$2:$B$100,"2nd Division") -> 699 | L4: =$K$2*B3+(1-$K$2)*L3 -> 408 | Q4: ='Model Comparison'!J3 -> 717.51953 | U4: =_xlfn.XLOOKUP("Best",'Model Comparison'!G5:G7, 'Model Comparison'!B5:B7) -> Exponential Smoothing | Y4: =MIN('Model Comparison'!C5:C7) -> 81.371652
A5: 2019 | B5: =SUMIFS(INDEX('Historical Data'!$C$2:$ZZ$100,0,MATCH(A5&"",'Historical Data'!$C$1:$ZZ$1,0)),'Historical Data'!$B$2:$B$100,"2nd Division") -> 623 | C5: =AVERAGE(B2:B4) -> 505 | D5: =B5-C5 -> 118 | E5: =ABS(D5) -> 118 | F5: =IFERROR(E5/B5,"") -> 0.1894061 | G5: =(B4*0.5)+(B3*0.3)+(B2*0.2) -> 547.6 | H5: =B5-G5 -> 75.4 | I5: =ABS(H5) -> 75.4 | J5: =IFERROR(I5/B5,"") -> 0.12102729 | L5: =$K$2*B4+(1-$K$2)*L4 -> 553.5 | M5: =B5-L5 -> 69.5 | N5: =ABS(M5) -> 69.5 | O5: =IFERROR(N5/B5,"") -> 0.11155698 | P5: =MAX(0,B5-L5) -> 69.5
A6: 2020 | B6: =SUMIFS(INDEX('Historical Data'!$C$2:$ZZ$100,0,MATCH(A6&"",'Historical Data'!$C$1:$ZZ$1,0)),'Historical Data'!$B$2:$B$100,"2nd Division") -> 807 | C6: =AVERAGE(B3:B5) -> 557 | D6: =B6-C6 -> 250 | E6: =ABS(D6) -> 250 | F6: =IFERROR(E6/B6,"") -> 0.30978934 | G6: =(B5*0.5)+(B4*0.3)+(B3*0.2) -> 591 | H6: =B6-G6 -> 216 | I6: =ABS(H6) -> 216 | J6: =IFERROR(I6/B6,"") -> 0.26765799 | L6: =$K$2*B5+(1-$K$2)*L5 -> 588.25 | M6: =B6-L6 -> 218.75 | N6: =ABS(M6) -> 218.75 | O6: =IFERROR(N6/B6,"") -> 0.27106568 | P6: =MAX(0,B6-L6) -> 218.75
A7: 2021 | B7: =SUMIFS(INDEX('Historical Data'!$C$2:$ZZ$100,0,MATCH(A7&"",'Historical Data'!$C$1:$ZZ$1,0)),'Historical Data'!$B$2:$B$100,"2nd Division") -> 609 | C7: =AVERAGE(B4:B6) -> 709.66667 | D7: =B7-C7 -> -100.66667 | E7: =ABS(D7) -> 100.66667 | F7: =IFERROR(E7/B7,"") -> 0.1652983 | G7: =(B6*0.5)+(B5*0.3)+(B4*0.2) -> 730.2 | H7: =B7-G7 -> -121.2 | I7: =ABS(H7) -> 121.2 | J7: =IFERROR(I7/B7,"") -> 0.19901478 | L7: =$K$2*B6+(1-$K$2)*L6 -> 697.625 | M7: =B7-L7 -> -88.625 | N7: =ABS(M7) -> 88.625 | O7: =IFERROR(N7/B7,"") -> 0.14552545 | P7: =MAX(0,B7-L7) -> 0
A8: 2022 | B8: =SUMIFS(INDEX('Historical Data'!$C$2:$ZZ$100,0,MATCH(A8&"",'Historical Data'!$C$1:$ZZ$1,0)),'Historical Data'!$B$2:$B$100,"2nd Division") -> 693 | C8: =AVERAGE(B5:B7) -> 679.66667 | D8: =B8-C8 -> 13.333333 | E8: =ABS(D8) -> 13.333333 | F8: =IFERROR(E8/B8,"") -> 0.019240019 | G8: =(B7*0.5)+(B6*0.3)+(B5*0.2) -> 671.2 | H8: =B8-G8 -> 21.8 | I8: =ABS(H8) -> 21.8 | J8: =IFERROR(I8/B8,"") -> 0.031457431 | L8: =$K$2*B7+(1-$K$2)*L7 -> 653.3125 | M8: =B8-L8 -> 39.6875 | N8: =ABS(M8) -> 39.6875 | O8: =IFERROR(N8/B8,"") -> 0.05726912 | P8: =MAX(0,B8-L8) -> 39.6875
A9: 2023 | B9: =SUMIFS(INDEX('Historical Data'!$C$2:$ZZ$100,0,MATCH(A9&"",'Historical Data'!$C$1:$ZZ$1,0)),'Historical Data'!$B$2:$B$100,"2nd Division") -> 641 | C9: =AVERAGE(B6:B8) -> 703 | D9: =B9-C9 -> -62 | E9: =ABS(D9) -> 62 | F9: =IFERROR(E9/B9,"") -> 0.096723869 | G9: =(B8*0.5)+(B7*0.3)+(B6*0.2) -> 690.6 | H9: =B9-G9 -> -49.6 | I9: =ABS(H9) -> 49.6 | J9: =IFERROR(I9/B9,"") -> 0.077379095 | L9: =$K$2*B8+(1-$K$2)*L8 -> 673.15625 | M9: =B9-L9 -> -32.15625 | N9: =ABS(M9) -> 32.15625 | O9: =IFERROR(N9/B9,"") -> 0.050165757 | P9: =MAX(0,B9-L9) -> 0
A10: 2024 | B10: =SUMIFS(INDEX('Historical Data'!$C$2:$ZZ$100,0,MATCH(A10&"",'Historical Data'!$C$1:$ZZ$1,0)),'Historical Data'!$B$2:$B$100,"2nd Division") -> 713 | C10: =AVERAGE(B7:B9) -> 647.66667 | D10: =B10-C10 -> 65.333333 | E10: =ABS(D10) -> 65.333333 | F10: =IFERROR(E10/B10,"") -> 0.091631604 | G10: =(B9*0.5)+(B8*0.3)+(B7*0.2) -> 650.2 | H10: =B10-G10 -> 62.8 | I10: =ABS(H10) -> 62.8 | J10: =IFERROR(I10/B10,"") -> 0.088078541 | L10: =$K$2*B9+(1-$K$2)*L9 -> 657.07812 | M10: =B10-L10 -> 55.921875 | N10: =ABS(M10) -> 55.921875 | O10: =IFERROR(N10/B10,"") -> 0.078431802 | P10: =MAX(0,B10-L10) -> 55.921875
A11: 2025 | B11: =SUMIFS(INDEX('Historical Data'!$C$2:$ZZ$100,0,MATCH(A11&"",'Historical Data'!$C$1:$ZZ$1,0)),'Historical Data'!$B$2:$B$100,"2nd Division") -> 750 | C11: =AVERAGE(B8:B10) -> 682.33333 | D11: =B11-C11 -> 67.666667 | E11: =ABS(D11) -> 67.666667 | F11: =IFERROR(E11/B11,"") -> 0.090222222 | G11: =(B10*0.5)+(B9*0.3)+(B8*0.2) -> 687.4 | H11: =B11-G11 -> 62.6 | I11: =ABS(H11) -> 62.6 | J11: =IFERROR(I11/B11,"") -> 0.083466667 | L11: =$K$2*B10+(1-$K$2)*L10 -> 685.03906 | M11: =B11-L11 -> 64.960938 | N11: =ABS(M11) -> 64.960938 | O11: =IFERROR(N11/B11,"") -> 0.086614583 | P11: =MAX(0,B11-L11) -> 64.960938
D12: =AVERAGE(D5:D11) -> 50.238095 | E12: =AVERAGE(E5:E11) -> 96.714286 | F12: =AVERAGE(F5:F11) -> 0.13747307 | H12: =AVERAGE(H5:H11) -> 38.257143 | I12: =AVERAGE(I5:I11) -> 87.057143 | J12: =AVERAGE(J5:J11) -> 0.12401168 | M12: =AVERAGE(M5:M11) -> 46.862723 | N12: =AVERAGE(N5:N11) -> 81.371652 | O12: =AVERAGE(O5:O11) -> 0.11437562
A14: 2026 | B14: =IF(COUNT('Historical Data'!M3,'Historical Data'!M6,'Historical Data'!M9,'Historical Data'!M12,'Historical Data'!M15,'Historical Data'!M18,'Historical Data'!M21)=7,SUM('Historical Data'!M3,'Historical Data'!M6,'Historical Data'!M9,'Historical Data'!M12,'Historical Data'!M15,'Historical Data'!M18,'Historical Data'!M21),"") | C14: =AVERAGE(B9:B11) -> 701.33333 | G14: =(B11*0.5)+(B10*0.3)+(B9*0.2) -> 717.1 | L14: =$K$2*B11+(1-$K$2)*L11 -> 717.51953
A15: 2027 | L15: =IF(ISNUMBER(B14),$K$2*B14+(1-$K$2)*L14,L14) -> 717.51953
L18: Maximum Underforecast | M18: =MAX(P5:P11) -> 218.75
L19: Average Underforecast | M19: =AVERAGE(P5:P11) -> 64.117188
L20: Historical Coverage | M20: =COUNTIF(P5:P11, "<=96")/COUNT(P5:P11) -> 0.85714286

Sheet 3rd Division
A1: Year | B1: Actual Demand | C1: Average Forecast | D1: Error | E1: Absolute Error | F1: Absolute % Error | G1: Weighted Forecast | H1: Error | I1: Absolute Error | J1: Absolute % Error | K1: Alpha | L1: Exponential Smoothing | M1: Error | N1: Absolute Error | O1: Absolute % Error
A2: 2016 | B2: =SUMIFS(INDEX('Historical Data'!$C$2:$ZZ$100,0,MATCH(A2&"",'Historical Data'!$C$1:$ZZ$1,0)),'Historical Data'!$B$2:$B$100,"3rd Division") -> 364 | K2: 0.5 | Q2: 2026 FORECAST | U2: BEST MODEL | Y2: HISTORICAL MAE
A3: 2017 | B3: =SUMIFS(INDEX('Historical Data'!$C$2:$ZZ$100,0,MATCH(A3&"",'Historical Data'!$C$1:$ZZ$1,0)),'Historical Data'!$B$2:$B$100,"3rd Division") -> 377 | L3: =B2 -> 364
A4: 2018 | B4: =SUMIFS(INDEX('Historical Data'!$C$2:$ZZ$100,0,MATCH(A4&"",'Historical Data'!$C$1:$ZZ$1,0)),'Historical Data'!$B$2:$B$100,"3rd Division") -> 686 | L4: =$K$2*B3+(1-$K$2)*L3 -> 370.5 | Q4: ='Model Comparison'!J4 -> 642 | U4: =_xlfn.XLOOKUP("Best",'Model Comparison'!G8:G10, 'Model Comparison'!B8:B10) -> Weighted Moving Average | Y4: =MIN('Model Comparison'!C8:C10) -> 86.685714
A5: 2019 | B5: =SUMIFS(INDEX('Historical Data'!$C$2:$ZZ$100,0,MATCH(A5&"",'Historical Data'!$C$1:$ZZ$1,0)),'Historical Data'!$B$2:$B$100,"3rd Division") -> 805 | C5: =AVERAGE(B2:B4) -> 475.66667 | D5: =B5-C5 -> 329.33333 | E5: =ABS(D5) -> 329.33333 | F5: =IFERROR(E5/B5,"") -> 0.40910973 | G5: =(B4*0.5)+(B3*0.3)+(B2*0.2) -> 528.9 | H5: =B5-G5 -> 276.1 | I5: =ABS(H5) -> 276.1 | J5: =IFERROR(I5/B5,"") -> 0.34298137 | L5: =$K$2*B4+(1-$K$2)*L4 -> 528.25 | M5: =B5-L5 -> 276.75 | N5: =ABS(M5) -> 276.75 | O5: =IFERROR(N5/B5,"") -> 0.34378882 | P5: =MAX(0,B5-G5) -> 276.1
A6: 2020 | B6: =SUMIFS(INDEX('Historical Data'!$C$2:$ZZ$100,0,MATCH(A6&"",'Historical Data'!$C$1:$ZZ$1,0)),'Historical Data'!$B$2:$B$100,"3rd Division") -> 731 | C6: =AVERAGE(B3:B5) -> 622.66667 | D6: =B6-C6 -> 108.33333 | E6: =ABS(D6) -> 108.33333 | F6: =IFERROR(E6/B6,"") -> 0.14819881 | G6: =(B5*0.5)+(B4*0.3)+(B3*0.2) -> 683.7 | H6: =B6-G6 -> 47.3 | I6: =ABS(H6) -> 47.3 | J6: =IFERROR(I6/B6,"") -> 0.064705882 | L6: =$K$2*B5+(1-$K$2)*L5 -> 666.625 | M6: =B6-L6 -> 64.375 | N6: =ABS(M6) -> 64.375 | O6: =IFERROR(N6/B6,"") -> 0.088064295 | P6: =MAX(0,B6-G6) -> 47.3
A7: 2021 | B7: =SUMIFS(INDEX('Historical Data'!$C$2:$ZZ$100,0,MATCH(A7&"",'Historical Data'!$C$1:$ZZ$1,0)),'Historical Data'!$B$2:$B$100,"3rd Division") -> 730 | C7: =AVERAGE(B4:B6) -> 740.66667 | D7: =B7-C7 -> -10.666667 | E7: =ABS(D7) -> 10.666667 | F7: =IFERROR(E7/B7,"") -> 0.014611872 | G7: =(B6*0.5)+(B5*0.3)+(B4*0.2) -> 744.2 | H7: =B7-G7 -> -14.2 | I7: =ABS(H7) -> 14.2 | J7: =IFERROR(I7/B7,"") -> 0.019452055 | L7: =$K$2*B6+(1-$K$2)*L6 -> 698.8125 | M7: =B7-L7 -> 31.1875 | N7: =ABS(M7) -> 31.1875 | O7: =IFERROR(N7/B7,"") -> 0.042722603 | P7: =MAX(0,B7-G7) -> 0
A8: 2022 | B8: =SUMIFS(INDEX('Historical Data'!$C$2:$ZZ$100,0,MATCH(A8&"",'Historical Data'!$C$1:$ZZ$1,0)),'Historical Data'!$B$2:$B$100,"3rd Division") -> 737 | C8: =AVERAGE(B5:B7) -> 755.33333 | D8: =B8-C8 -> -18.333333 | E8: =ABS(D8) -> 18.333333 | F8: =IFERROR(E8/B8,"") -> 0.024875622 | G8: =(B7*0.5)+(B6*0.3)+(B5*0.2) -> 745.3 | H8: =B8-G8 -> -8.3 | I8: =ABS(H8) -> 8.3 | J8: =IFERROR(I8/B8,"") -> 0.011261872 | L8: =$K$2*B7+(1-$K$2)*L7 -> 714.40625 | M8: =B8-L8 -> 22.59375 | N8: =ABS(M8) -> 22.59375 | O8: =IFERROR(N8/B8,"") -> 0.030656377 | P8: =MAX(0,B8-G8) -> 0
A9: 2023 | B9: =SUMIFS(INDEX('Historical Data'!$C$2:$ZZ$100,0,MATCH(A9&"",'Historical Data'!$C$1:$ZZ$1,0)),'Historical Data'!$B$2:$B$100,"3rd Division") -> 688 | C9: =AVERAGE(B6:B8) -> 732.66667 | D9: =B9-C9 -> -44.666667 | E9: =ABS(D9) -> 44.666667 | F9: =IFERROR(E9/B9,"") -> 0.064922481 | G9: =(B8*0.5)+(B7*0.3)+(B6*0.2) -> 733.7 | H9: =B9-G9 -> -45.7 | I9: =ABS(H9) -> 45.7 | J9: =IFERROR(I9/B9,"") -> 0.066424419 | L9: =$K$2*B8+(1-$K$2)*L8 -> 725.70312 | M9: =B9-L9 -> -37.703125 | N9: =ABS(M9) -> 37.703125 | O9: =IFERROR(N9/B9,"") -> 0.054801054 | P9: =MAX(0,B9-G9) -> 0
A10: 2024 | B10: =SUMIFS(INDEX('Historical Data'!$C$2:$ZZ$100,0,MATCH(A10&"",'Historical Data'!$C$1:$ZZ$1,0)),'Historical Data'!$B$2:$B$100,"3rd Division") -> 753 | C10: =AVERAGE(B7:B9) -> 718.33333 | D10: =B10-C10 -> 34.666667 | E10: =ABS(D10) -> 34.666667 | F10: =IFERROR(E10/B10,"") -> 0.04603807 | G10: =(B9*0.5)+(B8*0.3)+(B7*0.2) -> 711.1 | H10: =B10-G10 -> 41.9 | I10: =ABS(H10) -> 41.9 | J10: =IFERROR(I10/B10,"") -> 0.05564409 | L10: =$K$2*B9+(1-$K$2)*L9 -> 706.85156 | M10: =B10-L10 -> 46.148438 | N10: =ABS(M10) -> 46.148438 | O10: =IFERROR(N10/B10,"") -> 0.061286106 | P10: =MAX(0,B10-G10) -> 41.9
A11: 2025 | B11: =SUMIFS(INDEX('Historical Data'!$C$2:$ZZ$100,0,MATCH(A11&"",'Historical Data'!$C$1:$ZZ$1,0)),'Historical Data'!$B$2:$B$100,"3rd Division") -> 557 | C11: =AVERAGE(B8:B10) -> 726 | D11: =B11-C11 -> -169 | E11: =ABS(D11) -> 169 | F11: =IFERROR(E11/B11,"") -> 0.30341113 | G11: =(B10*0.5)+(B9*0.3)+(B8*0.2) -> 730.3 | H11: =B11-G11 -> -173.3 | I11: =ABS(H11) -> 173.3 | J11: =IFERROR(I11/B11,"") -> 0.31113106 | L11: =$K$2*B10+(1-$K$2)*L10 -> 729.92578 | M11: =B11-L11 -> -172.92578 | N11: =ABS(M11) -> 172.92578 | O11: =IFERROR(N11/B11,"") -> 0.31045921 | P11: =MAX(0,B11-G11) -> 0
D12: =AVERAGE(D5:D11) -> 32.809524 | E12: =AVERAGE(E5:E11) -> 102.14286 | F12: =AVERAGE(F5:F11) -> 0.14445253 | H12: =AVERAGE(H5:H11) -> 17.685714 | I12: =AVERAGE(I5:I11) -> 86.685714 | J12: =AVERAGE(J5:J11) -> 0.12451439 | M12: =AVERAGE(M5:M11) -> 32.917969 | N12: =AVERAGE(N5:N11) -> 93.097656 | O12: =AVERAGE(O5:O11) -> 0.13311121
A14: 2026 | B14: =IF(COUNT('Historical Data'!M4,'Historical Data'!M7,'Historical Data'!M10,'Historical Data'!M13,'Historical Data'!M16,'Historical Data'!M19,'Historical Data'!M22)=7,SUM('Historical Data'!M4,'Historical Data'!M7,'Historical Data'!M10,'Historical Data'!M13,'Historical Data'!M16,'Historical Data'!M19,'Historical Data'!M22),"") | C14: =AVERAGE(B9:B11) -> 666 | G14: =(B11*0.5)+(B10*0.3)+(B9*0.2) -> 642 | L14: =$K$2*B11+(1-$K$2)*L11 -> 643.46289
A15: 2027 | G15: =IF(ISNUMBER(B14),B14*0.5+B11*0.3+B10*0.2,G14*0.5+B11*0.3+B10*0.2) -> 638.7
L17: Maximum Underforecast | M17: =MAX(P5:P11) -> 276.1
L18: Average Underforecast | M18: =AVERAGE(P5:P11) -> 52.185714
L19: Historical Coverage | M19: =COUNTIF(P5:P11, "<=133")/COUNT(P5:P11) -> 0.85714286

Sheet Model Comparison
A1: Division | B1: Forecasting Model | C1: MAE | D1: MAPE | E1: Bias | F1: 2026 Forecast | G1: Best Model? | I1: Division | J1: 2026 Forecast | K1: 2027 Forecast
A2: 1st | B2: 3-Year Moving Average | C2: ='1st Division'!E12 -> 102.61905 | D2: ='1st Division'!F12 -> 0.14206775 | E2: ='1st Division'!D12 -> 51.47619 | F2: ='1st Division'!C14 -> 677.66667 | G2: =IF(C2=_xlfn.MINIFS($C$2:$C$10, $A$2:$A$10,A2), "Best","") | I2: 1st | J2: =SUMIFS($F$2:$F$10, $A$2:$A$10, I2,$G$2:$G$10,"Best") -> 708.69922 | K2: ='1st Division'!L15 -> 708.69922
A3: 1st | B3: Weighted Moving Average | C3: ='1st Division'!I12 -> 94.485714 | D3: ='1st Division'!J12 -> 0.13127585 | E3: ='1st Division'!H12 -> 41.314286 | F3: ='1st Division'!G14 -> 696.1 | G3: =IF(C3=_xlfn.MINIFS($C$2:$C$10, $A$2:$A$10,A3), "Best","") | I3: 2nd | J3: =SUMIFS($F$2:$F$10, $A$2:$A$10, I3,$G$2:$G$10,"Best") -> 717.51953 | K3: ='2nd Division'!L15 -> 717.51953
A4: 1st | B4: Exponential Smoothing | C4: ='1st Division'!N12 -> 92.739955 | D4: ='1st Division'!O12 -> 0.12760579 | E4: ='1st Division'!M12 -> 54.342634 | F4: ='1st Division'!L14 -> 708.69922 | G4: =IF(C4=_xlfn.MINIFS($C$2:$C$10, $A$2:$A$10,A4), "Best","") -> Best | I4: 3rd | J4: =SUMIFS($F$2:$F$10, $A$2:$A$10, I4,$G$2:$G$10,"Best") -> 642 | K4: ='3rd Division'!G15 -> 638.7
A5: 2nd | B5: 3-Year Moving Average | C5: ='2nd Division'!E12 -> 96.714286 | D5: ='2nd Division'!F12 -> 0.13747307 | E5: ='2nd Division'!D12 -> 50.238095 | F5: ='2nd Division'!C14 -> 701.33333 | G5: =IF(C5=_xlfn.MINIFS($C$2:$C$10, $A$2:$A$10,A5), "Best","")
A6: 2nd | B6: Weighted Moving Average | C6: ='2nd Division'!I12 -> 87.057143 | D6: ='2nd Division'!J12 -> 0.12401168 | E6: ='2nd Division'!H12 -> 38.257143 | F6: ='2nd Division'!G14 -> 717.1 | G6: =IF(C6=_xlfn.MINIFS($C$2:$C$10, $A$2:$A$10,A6), "Best","")
A7: 2nd | B7: Exponential Smoothing | C7: ='2nd Division'!N12 -> 81.371652 | D7: ='2nd Division'!O12 -> 0.11437562 | E7: ='2nd Division'!M12 -> 46.862723 | F7: ='2nd Division'!L14 -> 717.51953 | G7: =IF(C7=_xlfn.MINIFS($C$2:$C$10, $A$2:$A$10,A7), "Best","") -> Best
A8: 3rd | B8: 3-Year Moving Average | C8: ='3rd Division'!E12 -> 102.14286 | D8: ='3rd Division'!F12 -> 0.14445253 | E8: ='3rd Division'!D12 -> 32.809524 | F8: ='3rd Division'!C14 -> 666 | G8: =IF(C8=_xlfn.MINIFS($C$2:$C$10, $A$2:$A$10,A8), "Best","")
A9: 3rd | B9: Weighted Moving Average | C9: ='3rd Division'!I12 -> 86.685714 | D9: ='3rd Division'!J12 -> 0.12451439 | E9: ='3rd Division'!H12 -> 17.685714 | F9: ='3rd Division'!G14 -> 642 | G9: =IF(C9=_xlfn.MINIFS($C$2:$C$10, $A$2:$A$10,A9), "Best","") -> Best
A10: 3rd | B10: Exponential Smoothing | C10: ='3rd Division'!N12 -> 93.097656 | D10: ='3rd Division'!O12 -> 0.13311121 | E10: ='3rd Division'!M12 -> 32.917969 | F10: ='3rd Division'!L14 -> 643.46289 | G10: =IF(C10=_xlfn.MINIFS($C$2:$C$10, $A$2:$A$10,A10), "Best","")

Sheet Inventory Analysis
A1: Year | B1: Division | C1: Beginning Inventory | D1: Medals Purchased | E1: Medals Awarded | F1: Ending Inventory | G1: Inventory Adjustment | H1: Forecast Demand | I1: Projected Ending Inventory | J1: Historical MAE | K1: Safety Stock | L1: Risk-Adjusted Ending Inventory | M1: Target Inventory | N1: Recommended Purchase | O1: Projected Ending After Purchase | P1: Conservative Safety Stock | Q1: Conservative Recommended Purchase | R1: Additional Medals
A2: 2022 | B2: 1st Division | C2: =F2-D2+E2 -> 200 | D2: 745 | E2: =SUMIF(Table1[Medal Type],B2,INDEX(Table1[],0,MATCH(A2&"",Table1[#Headers],0))) -> 770 | F2: 175
A3: 2023 | B3: 1st Division | C3: =F2 -> 175 | D3: 639 | E3: =SUMIF(Table1[Medal Type],B3,INDEX(Table1[],0,MATCH(A3&"",Table1[#Headers],0))) -> 624 | F3: 190 | G3: =F3-(C3+D3-E3) -> 0
A4: 2024 | B4: 1st Division | C4: =F3 -> 190 | D4: 686 | E4: =SUMIF(Table1[Medal Type],B4,INDEX(Table1[],0,MATCH(A4&"",Table1[#Headers],0))) -> 666 | F4: 210 | G4: =F4-(C4+D4-E4) -> 0
A5: 2025 | B5: 1st Division | C5: =F4 -> 210 | D5: 758 | E5: =SUMIF(Table1[Medal Type],B5,INDEX(Table1[],0,MATCH(A5&"",Table1[#Headers],0))) -> 743 | F5: 225 | G5: =F5-(C5+D5-E5) -> 0
A6: 2026 | B6: 1st Division | C6: =F5 -> 225 | D6: 684 | E6: =IF(ISNUMBER('1st Division'!B14),SUMIF(Table1[Medal Type],B6,INDEX(Table1[],0,MATCH(A6&"",Table1[#Headers],0))),"") | G6: =IF(AND(ISNUMBER(E6),ISNUMBER(F6)),F6-(C6+D6-E6),"") | H6: ='Model Comparison'!J2 -> 708.69922 | I6: =C6+D6-ROUNDUP(H6,0) -> 200 | J6: =SUMIFS('Model Comparison'!$C$2:$C$10,'Model Comparison'!$A$2:$A$10,SUBSTITUTE(B6," Division",""),'Model Comparison'!$G$2:$G$10,"Best") -> 92.739955 | K6: =ROUNDUP(J6*2,0) -> 186 | L6: =I6-K6 -> 14
A7: 2027 | B7: 1st Division | C7: =IF(ISNUMBER(F6),F6,I6) -> 200 | H7: ='Model Comparison'!K2 -> 708.69922 | J7: =J6 -> 92.739955 | K7: =ROUNDUP(tblInventory[[#This Row],[Historical MAE]]*2,0) -> 186 | L7: =tblInventory[[#This Row],[Projected Ending After Purchase]]-tblInventory[[#This Row],[Safety Stock]] -> 0 | M7: =ROUNDUP(tblInventory[[#This Row],[Forecast Demand]],0)+tblInventory[[#This Row],[Safety Stock]] -> 895 | N7: =MAX(0,tblInventory[[#This Row],[Target Inventory]]-ROUNDDOWN(tblInventory[[#This Row],[Beginning Inventory]],0)) -> 695 | O7: =tblInventory[[#This Row],[Beginning Inventory]]+tblInventory[[#This Row],[Recommended Purchase]]-ROUNDUP(tblInventory[[#This Row],[Forecast Demand]],0) -> 186 | P7: =MAX(K7,ROUNDUP(MAX('1st Division'!$P$5:$P$11),0)) -> 201 | Q7: =MAX(0,ROUNDUP(H7,0)+P7-ROUNDDOWN(C7,0)) -> 710 | R7: =tblInventory[[#This Row],[Conservative Recommended Purchase]]-tblInventory[[#This Row],[Recommended Purchase]] -> 15
A8: 2022 | B8: 2nd Division | C8: =F8-D8+E8 -> 180 | D8: 673 | E8: =SUMIF(Table1[Medal Type],B8,INDEX(Table1[],0,MATCH(A8&"",Table1[#Headers],0))) -> 693 | F8: 160 | G8: =F8-(C8+D8-E8) -> 0
A9: 2023 | B9: 2nd Division | C9: =F8 -> 160 | D9: 656 | E9: =SUMIF(Table1[Medal Type],B9,INDEX(Table1[],0,MATCH(A9&"",Table1[#Headers],0))) -> 641 | F9: 175 | G9: =F9-(C9+D9-E9) -> 0
A10: 2024 | B10: 2nd Division | C10: =F9 -> 175 | D10: 723 | E10: =SUMIF(Table1[Medal Type],B10,INDEX(Table1[],0,MATCH(A10&"",Table1[#Headers],0))) -> 713 | F10: 185 | G10: =F10-(C10+D10-E10) -> 0
A11: 2025 | B11: 2nd Division | C11: =F10 -> 185 | D11: 760 | E11: =SUMIF(Table1[Medal Type],B11,INDEX(Table1[],0,MATCH(A11&"",Table1[#Headers],0))) -> 750 | F11: 195 | G11: =F11-(C11+D11-E11) -> 0
A12: 2026 | B12: 2nd Division | C12: =F11 -> 195 | D12: 703 | E12: =IF(ISNUMBER('2nd Division'!B14),SUMIF(Table1[Medal Type],B12,INDEX(Table1[],0,MATCH(A12&"",Table1[#Headers],0))),"") | G12: =IF(AND(ISNUMBER(E12),ISNUMBER(F12)),F12-(C12+D12-E12),"") | H12: ='Model Comparison'!J3 -> 717.51953 | I12: =C12+D12-ROUNDUP(H12,0) -> 180 | J12: =SUMIFS('Model Comparison'!$C$2:$C$10,'Model Comparison'!$A$2:$A$10,SUBSTITUTE(B12," Division",""),'Model Comparison'!$G$2:$G$10,"Best") -> 81.371652 | K12: =ROUNDUP(J12*2,0) -> 163 | L12: =I12-K12 -> 17
A13: 2027 | B13: 2nd Division | C13: =IF(ISNUMBER(F12),F12,I12) -> 180 | H13: ='Model Comparison'!K3 -> 717.51953 | J13: =J12 -> 81.371652 | K13: =ROUNDUP(tblInventory[[#This Row],[Historical MAE]]*2,0) -> 163 | L13: =tblInventory[[#This Row],[Projected Ending After Purchase]]-tblInventory[[#This Row],[Safety Stock]] -> 0 | M13: =ROUNDUP(tblInventory[[#This Row],[Forecast Demand]],0)+tblInventory[[#This Row],[Safety Stock]] -> 881 | N13: =MAX(0,tblInventory[[#This Row],[Target Inventory]]-ROUNDDOWN(tblInventory[[#This Row],[Beginning Inventory]],0)) -> 701 | O13: =tblInventory[[#This Row],[Beginning Inventory]]+tblInventory[[#This Row],[Recommended Purchase]]-ROUNDUP(tblInventory[[#This Row],[Forecast Demand]],0) -> 163 | P13: =MAX(K13,ROUNDUP(MAX('2nd Division'!$P$5:$P$11),0)) -> 219 | Q13: =MAX(0,ROUNDUP(H13,0)+P13-ROUNDDOWN(C13,0)) -> 757 | R13: =tblInventory[[#This Row],[Conservative Recommended Purchase]]-tblInventory[[#This Row],[Recommended Purchase]] -> 56
A14: 2022 | B14: 3rd Division | C14: =F14-D14+E14 -> 150 | D14: 727 | E14: =SUMIF(Table1[Medal Type],B14,INDEX(Table1[],0,MATCH(A14&"",Table1[#Headers],0))) -> 737 | F14: 140 | G14: =F14-(C14+D14-E14) -> 0
A15: 2023 | B15: 3rd Division | C15: =F14 -> 140 | D15: 703 | E15: =SUMIF(Table1[Medal Type],B15,INDEX(Table1[],0,MATCH(A15&"",Table1[#Headers],0))) -> 688 | F15: 155 | G15: =F15-(C15+D15-E15) -> 0
A16: 2024 | B16: 3rd Division | C16: =F15 -> 155 | D16: 768 | E16: =SUMIF(Table1[Medal Type],B16,INDEX(Table1[],0,MATCH(A16&"",Table1[#Headers],0))) -> 753 | F16: 170 | G16: =F16-(C16+D16-E16) -> 0
A17: 2025 | B17: 3rd Division | C17: =F16 -> 170 | D17: 572 | E17: =SUMIF(Table1[Medal Type],B17,INDEX(Table1[],0,MATCH(A17&"",Table1[#Headers],0))) -> 557 | F17: 185 | G17: =F17-(C17+D17-E17) -> 0
A18: 2026 | B18: 3rd Division | C18: =F17 -> 185 | D18: 627 | E18: =IF(ISNUMBER('3rd Division'!B14),SUMIF(Table1[Medal Type],B18,INDEX(Table1[],0,MATCH(A18&"",Table1[#Headers],0))),"") | G18: =IF(AND(ISNUMBER(E18),ISNUMBER(F18)),F18-(C18+D18-E18),"") | H18: ='Model Comparison'!J4 -> 642 | I18: =C18+D18-ROUNDUP(H18,0) -> 170 | J18: =SUMIFS('Model Comparison'!$C$2:$C$10,'Model Comparison'!$A$2:$A$10,SUBSTITUTE(B18," Division",""),'Model Comparison'!$G$2:$G$10,"Best") -> 86.685714 | K18: =ROUNDUP(J18*2,0) -> 174 | L18: =I18-K18 -> -4
A19: 2027 | B19: 3rd Division | C19: =IF(ISNUMBER(F18),F18,I18) -> 170 | H19: ='Model Comparison'!K4 -> 638.7 | J19: =J18 -> 86.685714 | K19: =ROUNDUP(tblInventory[[#This Row],[Historical MAE]]*2,0) -> 174 | L19: =tblInventory[[#This Row],[Projected Ending After Purchase]]-tblInventory[[#This Row],[Safety Stock]] -> 0 | M19: =ROUNDUP(tblInventory[[#This Row],[Forecast Demand]],0)+tblInventory[[#This Row],[Safety Stock]] -> 813 | N19: =MAX(0,tblInventory[[#This Row],[Target Inventory]]-ROUNDDOWN(tblInventory[[#This Row],[Beginning Inventory]],0)) -> 643 | O19: =tblInventory[[#This Row],[Beginning Inventory]]+tblInventory[[#This Row],[Recommended Purchase]]-ROUNDUP(tblInventory[[#This Row],[Forecast Demand]],0) -> 174 | P19: =MAX(K19,ROUNDUP(MAX('3rd Division'!$P$5:$P$11),0)) -> 277 | Q19: =MAX(0,ROUNDUP(H19,0)+P19-ROUNDDOWN(C19,0)) -> 746 | R19: =tblInventory[[#This Row],[Conservative Recommended Purchase]]-tblInventory[[#This Row],[Recommended Purchase]] -> 103
A23: 2026 demand and ending inventory are prelimary projections. Actual results will replace these estimates after the contest and inventory reconciliation.

Sheet 2027 Inventory Forecast
A1: 2027 Medal Purchasing Forecast
A3: Executive Dashboard | Synthetic Data | Preliminary Purchasing Recommendations
A6: BASELINE RECOMMENDATION | G6: CONSERVATIVE ALTERNATIVE
A7: ='Dashboard Data'!E2 -> 2039 | G7: ='Dashboard Data'!E3 -> 2213
A10: Medals to Purchase | G10: Medals to Purchase
A12: ='Dashboard Data'!F2 -> 6117 | G12: ='Dashboard Data'!F3 -> 6639
H15: COST OF ADDITIONAL PROTECTION
H17: Additional estimated cost
H18: ='Dashboard Data'!F6 -> 522
H22: Additional Medals | K22: ='Dashboard Data'!E5 -> 174
H24: Purchase Increase | K24: ='Dashboard Data'!F7 -> 0.085335949
H26: Additional Protection Against Historical Underforecasting
A30: Historical Forecast Risk | 2019-2025
A33: Division | E33: Baseline Coverage | I33: Additional Medals
A34: 1st Division | E34: ='Dashboard Data'!O3 -> 0.71428571 | I34: ='Dashboard Data'!P3 -> 15
A35: 2nd Division | E35: ='Dashboard Data'!O4 -> 0.85714286 | I35: ='Dashboard Data'!P4 -> 56
A36: 3rd Division | E36: ='Dashboard Data'!O5 -> 0.85714286 | I36: ='Dashboard Data'!P5 -> 103
A38: Historical coverage reflects the percentage of years (2019-2025) in which baseline safety stock would have absorbed forecast underestimation. Future results may differ.
A41: 2027 PURCHASING RECOMMENDATION
A43: ="The baseline forecast recommends purchasing "& TEXT('Dashboard Data'!E2,"#,##0")& " medals at an estimated cost of "& TEXT('Dashboard Data'!F2,"$#,##0.00")& ". The conservative alternative recommends "& TEXT('Dashboard Data'!E3,"#,##0")& " medals for approximately "& TEXT('Dashboard Data'!F6,"$#,##0.00")& " more, providing additional protection against historical underforecasting across the three divisions." -> The baseline forecast recommends purchasing 2,039 medals at an estimated cost of $6,117.00. The conservative alternative recommends 2,213 medals for approximately $522.00 more, providing additional protection against historical underforecasting across the three divisions.
A47: Preliminary estimates based on historical demand and forecasting errors. Update purchasing recommendations after 2026 actual demand, inventory reconciliation, and vendor pricing are confirmed.
A50: Forecast Assumptions & Methodology
A53: Forecast Period | F53: 2027 (preliminary)
A54: Historical Evaluation | F54: 2019-2025
A55: 1st Division | F55: Exponential Smoothing
A56: 2nd Division | F56: Exponential Smoothing
A57: 3rd Division | F57: Weighted Moving Average
A58: Baseline Safety Stock | F58: 2 x MAE, rounded up
A59: Conservative Safety Stock | F59: Greater of baseline buffer or maximum historical underforecast
A60: Estimated Landed Unit Cost | F60: $3.00 per medal
A61: 2027 purchasing quantities are preliminary. Recalculate after 2026 actual demand, inventory reconciliation, and updated vendor pricing becomes available. Shipping estimates are based on prior-years order.

Sheet Dashboard Data
A1: Description | B1: Value | D1: Purchasing Scenario | E1: Medals to Purchase | F1: Estimated Cost
A2: Base Medal Cost | B2: 2.85 | D2: Baseline | E2: =SUM('Inventory Analysis'!N7, 'Inventory Analysis'!N13, 'Inventory Analysis'!N19) -> 2039 | F2: =E2*'Dashboard Data'!$B$4 -> 6117 | H2: Division | I2: Baseline | J2: Conservative | L2: Division | M2: Baseline Safety Stock | N2: Maximum Underforecast | O2: Historical Coverage | P2: Additional Medals
A3: Estimated Shipping per Medal | B3: 0.15 | D3: Conservative | E3: =SUM('Inventory Analysis'!Q7, 'Inventory Analysis'!Q13, 'Inventory Analysis'!Q19) -> 2213 | F3: =E3*'Dashboard Data'!$B$4 -> 6639 | H3: 1st Division | I3: ='Inventory Analysis'!N7 -> 695 | J3: ='Inventory Analysis'!Q7 -> 710 | L3: 1st Division | M3: ='Inventory Analysis'!K7 -> 186 | N3: =MAX('1st Division'!P5:P11) -> 200.5 | O3: =COUNTIF('1st Division'!P5:P11, "<="&M3)/COUNT('1st Division'!P5:P11) -> 0.71428571 | P3: ='Inventory Analysis'!Q7-'Inventory Analysis'!N7 -> 15
A4: Estimated Landing Cost | B4: =B2+B3 -> 3 | H4: 2nd Division | I4: ='Inventory Analysis'!N13 -> 701 | J4: ='Inventory Analysis'!Q13 -> 757 | L4: 2nd Division | M4: ='Inventory Analysis'!K13 -> 163 | N4: =MAX('2nd Division'!P5:P11) -> 218.75 | O4: =COUNTIF('2nd Division'!P5:P11, "<="&M4)/COUNT('2nd Division'!P5:P11) -> 0.85714286 | P4: ='Inventory Analysis'!Q13-'Inventory Analysis'!N13 -> 56
D5: Additional Medals | E5: =E3-E2 -> 174 | H5: 3rd Division | I5: ='Inventory Analysis'!N19 -> 643 | J5: ='Inventory Analysis'!Q19 -> 746 | L5: 3rd Division | M5: ='Inventory Analysis'!K19 -> 174 | N5: =MAX('3rd Division'!P5:P11) -> 276.1 | O5: =COUNTIF('3rd Division'!P5:P11, "<="&M5)/COUNT('3rd Division'!P5:P11) -> 0.85714286 | P5: ='Inventory Analysis'!Q19-'Inventory Analysis'!N19 -> 103
D6: Additional Estimated Cost | F6: =F3-F2 -> 522
D7: Percentage Increase | F7: =IFERROR(E5/E2,0) -> 0.085335949
